nexus_api/__init__.py
nexus_api/_encoder.py
nexus_api/_nexus_api.py
nexus_api-1.0.6.dist-info/METADATA
nexus_api-1.0.6.dist-info/WHEEL
nexus_api-1.0.6.dist-info/top_level.txt
nexus_api-1.0.6.dist-info/RECORD
